evdspy/EVDSlocal/__init__.py
evdspy/EVDSlocal/common/__init__.py
evdspy/EVDSlocal/common/clear_cache_folder.py
evdspy/EVDSlocal/common/colors.py
evdspy/EVDSlocal/common/common_imports.py
evdspy/EVDSlocal/common/file_classes.py
evdspy/EVDSlocal/common/files.py
evdspy/EVDSlocal/common/folder_name_checks.py
evdspy/EVDSlocal/common/prog.py
evdspy/EVDSlocal/common/table.py
evdspy/EVDSlocal/common/url_clean.py
evdspy/EVDSlocal/components/__init__.py
evdspy/EVDSlocal/components/api_params.py
evdspy/EVDSlocal/components/api_params_enums.py
evdspy/EVDSlocal/components/bucket_from_series.py
evdspy/EVDSlocal/components/evds_files.py
evdspy/EVDSlocal/components/evds_seri_files.py
evdspy/EVDSlocal/components/excel_class.py
evdspy/EVDSlocal/components/options_class.py
evdspy/EVDSlocal/components/request_or_cache.py
evdspy/EVDSlocal/components/url_class.py
evdspy/EVDSlocal/config/__init__.py
evdspy/EVDSlocal/config/apikey_class.py
evdspy/EVDSlocal/config/config.py
evdspy/EVDSlocal/config/credentials_file.py
evdspy/EVDSlocal/config/dotenv.py
evdspy/EVDSlocal/console/__init__.py
evdspy/EVDSlocal/console/menu.py
evdspy/EVDSlocal/console/menu_async.py
evdspy/EVDSlocal/console/menu_logo_header.py
evdspy/EVDSlocal/console/panel.py
evdspy/EVDSlocal/console/proxy_for_menu.py
evdspy/EVDSlocal/console/screen.py
evdspy/EVDSlocal/helper/__init__.py
evdspy/EVDSlocal/helper/print_m.py
evdspy/EVDSlocal/index_requests/__init__.py
evdspy/EVDSlocal/index_requests/categories.py
evdspy/EVDSlocal/index_requests/data_models.py
evdspy/EVDSlocal/index_requests/datagroup_individual.py
evdspy/EVDSlocal/index_requests/datagroups.py
evdspy/EVDSlocal/index_requests/datagroups_extra.py
evdspy/EVDSlocal/index_requests/datagroups_initial.py
evdspy/EVDSlocal/index_requests/df_operations.py
evdspy/EVDSlocal/index_requests/error_classes_index.py
evdspy/EVDSlocal/index_requests/get_series_indexes.py
evdspy/EVDSlocal/index_requests/get_series_indexes_exp.py
evdspy/EVDSlocal/index_requests/get_series_indexes_utils.py
evdspy-1.1.42.dist-info/LICENSE
evdspy-1.1.42.dist-info/METADATA
evdspy-1.1.42.dist-info/WHEEL
evdspy-1.1.42.dist-info/entry_points.txt
evdspy-1.1.42.dist-info/RECORD
