Metadata-Version: 2.3
Name: evdspy
Version: 1.1.42
Summary: A versatile interface for the 'EDDS' (EVDS) API of the Central Bank of the Republic of Türkiye (https://evds2.tcmb.gov.tr/index.php?/evds/userDocs). This package allows users to easily access and manage economic data through a user-friendly menu function. It features a robust caching mechanism to enhance the efficiency of data requests by storing frequently accessed data for selected periods. Required API keys can be obtained by registering on the EVDS website.
License: MIT
Author: Sermet Pekin
Author-email: sermet.pekin@gmail.com
Requires-Python: >=3.9,<4.0
Classifier: Development Status :: 5 - Production/Stable
Classifier: Environment :: Console
Classifier: Framework :: IPython
Classifier: Intended Audience :: Developers
Classifier: License :: OSI Approved :: MIT License
Classifier: Operating System :: MacOS
Classifier: Operating System :: Microsoft :: Windows
Classifier: Operating System :: POSIX :: Linux
Classifier: Programming Language :: Python :: 3
Classifier: Programming Language :: Python :: 3.9
Classifier: Programming Language :: Python :: 3.10
Classifier: Programming Language :: Python :: 3.11
Classifier: Programming Language :: Python :: 3.12
Classifier: Programming Language :: Python :: 3.13
Classifier: Typing :: Typed
Provides-Extra: jupyter
Requires-Dist: openpyxl (>3.0.10)
Requires-Dist: pandas (>1.5.0)
Requires-Dist: pytest (>=7.0.0)
Requires-Dist: python-dotenv (>=1.0.0)
Requires-Dist: requests (>=2.28.1)
Requires-Dist: rich (>=12.5.1)
Project-URL: Documentation, https://evdspy-repo.readthedocs.io/en/latest/home.html
Project-URL: Homepage, https://github.com/SermetPekin/evdspy-repo
